cwbplot/IO_tools.py
cwbplot/__init__.py
cwbplot/cwb_colorbar.py
cwbplot/dia.py
cwbplot/opdata.py
cwbplot/plotnc.py
cwbplot/projinfo.py
cwbplot/tools.py
cwbplot/tytrack.py
cwbplot/fonts/TaipeiSansTCBeta-Bold.ttf
cwbplot/fonts/TaipeiSansTCBeta-Regular.ttf
cwbplot/fonts/TaipeiSansTCBeta.ttf
cwbplot/fonts/TaipeiSansTCBetabd.ttf
cwbplot/fonts/bentham.ttf
cwbplot/fonts/blue-highway.ttf
cwbplot/fonts/blue-highwaybd.ttf
cwbplot/fonts/caliban.ttf
cwbplot/fonts/carlito.ttf
cwbplot/fonts/carlitobd.ttf
cwbplot/fonts/expressway-free.ttf
cwbplot/fonts/raleway.ttf
cwbplot/fonts/ralewaybd.ttf
cwbplot/fonts/rosario.ttf
cwbplot/fonts/rosariobd.ttf
cwbplot/fonts/times.ttf
cwbplot/fonts/timesbd.ttf
cwbplot/fonts/timesbi.ttf
cwbplot/fonts/timesi.ttf
cwbplot/sharedata/MREF_lonlat.npy
cwbplot/sharedata/Proj_Python_Scale005_1350x1350
cwbplot/sharedata/Proj_Python_Scale050_2750x2750
cwbplot/sharedata/RWRFLONLAT.npy
cwbplot/sharedata/WRFM04D01LONLAT.npy
cwbplot/sharedata/WRFM04D02LONLAT.npy
cwbplot/sharedata/WRFM04F02LONLAT.npy
cwbplot/sharedata/X00LATWD01H0254485
cwbplot/sharedata/X00LATWD02H0779334
cwbplot/sharedata/X00LATWE01H0202500
cwbplot/sharedata/X00LATWF01H0028067
cwbplot/sharedata/X00LATWF02H0079689
cwbplot/sharedata/X00LONWD01H0254485
cwbplot/sharedata/X00LONWD02H0779334
cwbplot/sharedata/X00LONWE01H0202500
cwbplot/sharedata/X00LONWF01H0028067
cwbplot/sharedata/X00LONWF02H0079689
cwbplot-0.0.8.dist-info/LICENSE
cwbplot-0.0.8.dist-info/METADATA
cwbplot-0.0.8.dist-info/WHEEL
cwbplot-0.0.8.dist-info/top_level.txt
cwbplot-0.0.8.dist-info/RECORD
