Metadata-Version: 2.1
Name: cwbplot
Version: 0.0.8
Summary: Central weather bureau rfs team and open data useful tool for daily wrok.
Home-page: https://github.com/Liu-CWB/cwbplot
Author: cwbrfsteam
Author-email: littlepon4@hotmail.com
License: MIT
Project-URL: Source, https://github.com/Liu-CWB/cwbplot
Classifier: Development Status :: 1 - Planning
Classifier: License :: OSI Approved :: MIT License
Classifier: Intended Audience :: System Administrators
Classifier: Intended Audience :: Developers
Classifier: Programming Language :: Python :: 3 :: Only
Requires-Python: >=3.6
License-File: LICENSE
Requires-Dist: pandas (>=1.0.3)
Requires-Dist: numpy (>=1.17.3)
Requires-Dist: matplotlib (<3.5.0,>=3.3.3)
Requires-Dist: pygrib (>=2.0.4)
Requires-Dist: requests (>=2.25.0)
Requires-Dist: netcdf4 (<=1.6.0,>=1.5.6)
Requires-Dist: basemap (>=1.3.0)
Requires-Dist: basemap-data (>=1.3.0)
Requires-Dist: basemap-data-hires (>=1.3.0)
Requires-Dist: xmltodict (>=0.12.0)
Provides-Extra: geotiff
Requires-Dist: gdal (>=2.4.1) ; extra == 'geotiff'
